opyml/__init__.py
opyml/body.py
opyml/head.py
opyml/opml.py
opyml/outline.py
opyml/util.py
opyml-0.1.2.dist-info/WHEEL
opyml-0.1.2.dist-info/METADATA
opyml-0.1.2.dist-info/RECORD
