Metadata-Version: 2.1
Name: opyml
Version: 0.1.2
Summary: OPML library for Python.
Home-page: https://git.bauke.xyz/Holllo/opyml
License: MIT OR Apache-2.0
Author: Holllo
Author-email: helllo@holllo.cc
Requires-Python: >=3.10,<4.0
Classifier: License :: Other/Proprietary License
Classifier: Programming Language :: Python :: 3
Classifier: Programming Language :: Python :: 3.10
Requires-Dist: defusedxml (>=0.7.1,<0.8.0)
Project-URL: Repository, https://git.bauke.xyz/Holllo/opyml
